LICENSE
clichessdrill/__init__.py
clichessdrill/game.py
clichessdrill/main.py
clichessdrill/menu.py
clichessdrill/pieces.py
clichessdrill/state.py
docs/screenshots/game_play_1.png
docs/screenshots/game_play_2.png
docs/screenshots/game_play_3.png
game_plans/default.json
clichessdrill-0.2.2.dist-info/entry_points.txt
clichessdrill-0.2.2.dist-info/LICENSE
clichessdrill-0.2.2.dist-info/WHEEL
clichessdrill-0.2.2.dist-info/METADATA
clichessdrill-0.2.2.dist-info/RECORD
