Metadata-Version: 2.1
Name: clichessdrill
Version: 0.2.2
Summary: 
Home-page: https://github.com/danielschweigert/clichessdrill
License: MIT
Author: Daniel Schweigert
Author-email: dan.schweigert@gmail.com
Requires-Python: >=3.8,<4.0
Classifier: License :: OSI Approved :: MIT License
Classifier: Programming Language :: Python :: 3
Classifier: Programming Language :: Python :: 3.10
Classifier: Programming Language :: Python :: 3.8
Classifier: Programming Language :: Python :: 3.9
Requires-Dist: chess (>=1.9.0,<2.0.0)
Requires-Dist: python-chess (>=1.999,<2.0)
Project-URL: Repository, https://github.com/danielschweigert/clichessdrill
